MANIFEST.in
README.rst
inigo.py
setup.py
version.txt
inigo.egg-info/PKG-INFO
inigo.egg-info/SOURCES.txt
inigo.egg-info/dependency_links.txt
inigo.egg-info/top_level.txt