Metadata-Version: 1.0
Name: inigo
Version: 1.0
Summary: Decaying list data structure
Home-page: http://github.com/MostAwesomeDude/inigo
Author: Corbin Simpson
Author-email: cds@corbinsimpson.com
License: MIT/X11
Platform: UNKNOWN
